pybrake/__init__.py
pybrake/aiohttp.py
pybrake/blocklist_filter.py
pybrake/celery.py
pybrake/code_hunks.py
pybrake/django.py
pybrake/flask.py
pybrake/git.py
pybrake/global_notifier.py
pybrake/logging.py
pybrake/metrics.py
pybrake/notice.py
pybrake/notifier.py
pybrake/notifier_name.py
pybrake/queries.py
pybrake/queues.py
pybrake/remote_settings.py
pybrake/route_metric.py
pybrake/routes.py
pybrake/settings_data.py
pybrake/tdigest.py
pybrake/test_celery.py
pybrake/test_celery_integration.py
pybrake/test_git.py
pybrake/test_helper.py
pybrake/test_logging.py
pybrake/test_notice.py
pybrake/test_notifier.py
pybrake/test_settings_data.py
pybrake/test_tdigest.py
pybrake/utils.py
pybrake/version.py
pybrake-1.0.3.dist-info/LICENSE
pybrake-1.0.3.dist-info/METADATA
pybrake-1.0.3.dist-info/WHEEL
pybrake-1.0.3.dist-info/top_level.txt
pybrake-1.0.3.dist-info/RECORD
