Metadata-Version: 2.1
Name: pybrake
Version: 1.0.3
Summary: Python exception notifier for Airbrake
Home-page: http://github.com/airbrake/pybrake
Author: Vladimir Mihailenco
Author-email: vlad@airbrake.io
License: MIT
Keywords: airbrake exception error notifier
Platform: UNKNOWN
Classifier: Development Status :: 3 - Alpha
Classifier: License :: OSI Approved :: MIT License
Classifier: Programming Language :: Python :: 3.6
Classifier: Programming Language :: Python :: 3.7
Classifier: Programming Language :: Python :: 3.8
Classifier: Topic :: Software Development
Requires-Dist: tdigest
